Workbook

Sheet portfolios
C2: Reference | D2: Strategic Asset Allocation
B3: Investment Grade Fixed Income | C3: 0.5 | D3: 0.36
B4: US Dollar Debt | C4: 50 | D4: 36
B5: Other Fixed Income | C5: 0 | D5: 0.045
B6: US High Yield | C6: 0 | D6: 4.5
B7: Public Equity | C7: 0.5 | D7: 0.355
B8: Global Equities (ACWI) | C8: 50 | D8: 0
B9: US Large Cap Growth Equity | C9: 0 | D9: 10
B10: US Large Cap Value Equity | C10: 0 | D10: 11.2
B11: US Small Cap Equity | C11: 0 | D11: 3.5
B12: Europe ex-UK Equity | C12: 0 | D12: 4
B13: UK Equity | C13: 0 | D13: 1.2
B14: Japanese Equity | C14: 0 | D14: 1.8
... B36: Volatility | C36: 0.073904498 | D36: 0.075095139

Sheet Risk Decomposition
B1: 0
A2: US Dollar Debt | B2: 0.0086024743
A3: US High Yield | B3: 0.0328015
A4: US Equity | B4: =SUM(B5:B7) -> 0.45827215
A5: US Large Cap Growth Equity | B5: 0.19740878
A6: US Large Cap Value Equity | B6: 0.18908472
A7: US Small Cap Equity | B7: 0.071778651
A8: Europe ex-UK Equity | B8: 0.073157781
A9: UK Equity | B9: 0.018723684
A10: Japanese Equity | B10: 0.029793399
A11: Asia-Pacific Equity | B11: 0.015497621
A12: Emerging Market Equity | B12: 0.019727578
A13: Global REITs | B13: 0.010115146
A14: Infrastructure Equity | B14: 0.011798198
A15: Event Driven | B15: 0.0051275848
A16: Equity Long/Short | B16: 0.015793801
... A23: Infrastructure | B23: 0.022809738
B31: 0
A32: US Dollar Debt | B32: 0
A33: US Dollar Short Duration Debt | B33: 0
A34: US Corporate Bonds | B34: 0
A35: US High Yield | B35: 0
A36: EM External Debt | B36: 0
A37: Global Equities (ACWI) | B37: 0
A38: US Large Cap Growth Equity | B38: 0
A39: US Large Cap Value Equity | B39: 0
A40: US Small Cap Equity | B40: 0
A41: EUR | B41: 0.019086595
A42: GBP | B42: 0.0066725976
A43: JPY | B43: 0.0035395217
... A56: Infrastructure | B56: 0

Sheet Currency Hedging
B2: Scenario | C2: Volatility
B3: 0 | C3: 0.076140075
B4: 0.5 | C4: 0.075265246
B5: 0.7 | C5: 0.074936639
B6: 1 | C6: 0.074466879

Sheet Risk Premias
C1: 0
A2: 7 | B2: Total | C2: =SUM(C3:C8) -> 0.039323105
A3: 6 | B3: Emerging Market | C3: 0.00070898095
A4: 5 | B4: Carry | C4: -7.3142573e-05
A5: 4 | B5: Liquidity | C5: 0.0052595581
A6: 3 | B6: Leverage | C6: 0.0032283957
A7: 2 | B7: Term | C7: 0.0059454343
A8: 1 | B8: Equity | C8: 0.024253878
C31: 0
A32: 10 | B32: Commodities | C32: 0.0047471589
A33: 9 | B33: Value | C33: -0.0018207882
A34: 8 | B34: Size | C34: 0.023367737
A35: 7 | B35: Momentum | C35: 0.0083822687
A36: 6 | B36: Emerging Market | C36: 0.0034695735
A37: 5 | B37: Carry | C37: 0.0073740407
A38: 4 | B38: Liquidity | C38: 0.03714891
A39: 3 | B39: Leverage | C39: 0.0088779764
A40: 2 | B40: Term | C40: 0.014306171
A41: 1 | B41: Equity | C41: 0.85138065

Sheet risk_dashboard
B1: Reference | D1: Strategic Asset Allocation
A2: Investment Grade Fixed Income | B2: 0.5 | D2: 0.36
A3: Other Fixed Income | B3: - | D3: 0.045
A4: Public Equity | B4: 0.5 | D4: 0.355
A5: Hedge Funds | B5: - | D5: 0.045
A6: Private Equity | B6: - | D6: 0.12
A7: Other Private Assets | B7: - | D7: 0.075
A8: Estimated Mean Return | B8: 0.053832603 | D8: 0.064431105
A9: Sharpe Ratio | B9: 0.39013326 | D9: 0.52364381
A10: Volatility | B10: 0.073904498 | D10: 0.075095139
A11: Factor Based Risk Analytics
A12: Predicted Performance Over Stress Periods | B12: Nominal | C12: Real | D12: Nominal | E12: Real
A13: Oil Embargo (Jan | B13: -0.17760179 | C13: -0.30112279 | D13: -0.18055611 | E13: -0.30363338
A14: US Inflation / Iranian Revolution | B14: 0.091966297 | C14: -0.079811031 | D14: 0.078775544 | E14: -0.090926746
A15: US Stagflation | B15: 0.033833922 | C15: -0.092351672 | D15: 0.064064379 | E15: -0.065811022
A16: Black Monday | B16: -0.093805688 | C16: -0.096177114 | D16: -0.097941055 | E16: -0.10030166
A17: Bond Crisis | B17: -0.031535849 | C17: -0.054164175 | D17: -0.027653506 | E17: -0.050372543
A18: Russian Default / LTCM Collapse | B18: -0.067084778 | C18: -0.068230254 | D18: -0.079916796 | E18: -0.081046516
A19: Tech Meltdown | B19: -0.18876721 | C19: -0.23274034 | D19: -0.14094079 | E19: -0.18750637
A20: Financial Crisis | B20: -0.25987242 | C20: -0.27210456 | D20: -0.29538144 | E20: -0.30702671
A21: Covid-19 | B21: -0.089207424 | C21: -0.085983284 | D21: -0.10925781 | E21: -0.10610465
A22: Value at Risk with 99% Confidence
A23: Over 1 Month | B23: 0.05434373 | C23: 0.056344567 | D23: 0.057861316 | E23: 0.059854711
A24: Over 1 Year | B24: 0.16233352 | C24: 0.18120457 | D24: 0.19742361 | E24: 0.2151283
A25: Over 3 Years | B25: 0.19098418 | C25: 0.24478439 | D25: 0.18238034 | E25: 0.23231298
A26: Conditional Value at Risk with 99% Confidence
A27: Over 1 Month | B27: 0.07186401 | C27: 0.073827777 | D27: 0.080236346 | E27: 0.082182399
A28: Over 1 Year | B28: 0.19741636 | C28: 0.21563136 | D28: 0.22128131 | E28: 0.24041735
A29: Over 3 Years | B29: 0.24037888 | C29: 0.28832371 | D29: 0.23717115 | E29: 0.28471073
A30: Probability of Loss
A31: Over 1 Month | B31: 0.3473 | C31: 0.3883 | D31: 0.30495 | E31: 0.3462
A32: Over 1 Year | B32: 0.19 | C32: 0.26275 | D32: 0.16595 | E32: 0.23295
A33: Over 3 Years | B33: 0.1142 | C33: 0.19855 | D33: 0.09155 | E33: 0.1582
A34: Portfolio Risk Premia

Sheet assumptions
B1: Long-Term Estimates | I1: Modelling Dates
B2: Risk Premia with Estimated Range | E2: Volatility | F2: Sharpe Ratio | G2: Estimated Mean Return (2.5% Risk Free Rate) | H2: Hedging Ratio | I2: From | J2: To
A3: Investment Grade Fixed Income
A4: US Dollar Debt | B4: 0.0057327167 | C4: 0.010867352 | D4: 0.016001987 | E4: 0.03211081 | F4: 0.33843281 | G4: 0.035867352 | H4: 0 | I4: 26723 | J4: 45777
A5: US Dollar Short Duration Debt | B5: 0.00043830452 | C5: 0.0030901253 | D5: 0.0057419461 | E5: 0.014730739 | F5: 0.20977395 | G5: 0.028090125 | H5: 0 | I5: 33662 | J5: 45777
A6: US Corporate Bonds | B6: 0.013188134 | C6: 0.019942198 | D6: 0.026696262 | E6: 0.042238343 | F6: 0.47213496 | G6: 0.044942198 | H6: 0 | I6: 26723 | J6: 45777
A7: Other Fixed Income
A8: US High Yield | B8: 0.019835863 | C8: 0.0329573 | D8: 0.046078736 | E8: 0.082058406 | F8: 0.40163222 | G8: 0.0579573 | H8: 0 | I8: 30559 | J8: 45777
A9: EM External Debt | B9: 0.024425402 | C9: 0.047110684 | D9: 0.069795967 | E9: 0.12201962 | F9: 0.38609106 | G9: 0.072110684 | H9: 0 | I9: 34365 | J9: 45107
A10: Public Equity
A11: Global Equities (ACWI) | B11: 0.021935922 | C11: 0.046797853 | D11: 0.071659785 | E11: 0.1469643 | F11: 0.31843007 | G11: 0.071797853 | H11: 0.7 | I11: 32171 | J11: 45777
A12: US Large Cap Growth Equity | B12: 0.01717616 | C12: 0.044244823 | D12: 0.071313487 | E12: 0.16928111 | F12: 0.26136894 | G12: 0.069244823 | H12: 0 | I12: 28886 | J12: 45777
A13: US Large Cap Value Equity | B13: 0.038328393 | C13: 0.061473145 | D13: 0.084617896 | E13: 0.14474188 | F13: 0.42470877 | G13: 0.086473145 | H13: 0 | I13: 28886 | J13: 45777
A14: US Small Cap Equity | B14: 0.039548089 | C14: 0.070287621 | D14: 0.10102715 | E14: 0.19223787 | F14: 0.36562838 | G14: 0.095287621 | H14: 0 | I14: 28886 | J14: 45777
A15: Europe ex-UK Equity | B15: 0.021019364 | C15: 0.047103365 | D15: 0.073187365 | E15: 0.16312326 | F15: 0.28875934 | G15: 0.072103365 | H15: 0.7 | I15: 25626 | J15: 45777
A16: UK Equity | B16: 0.025370931 | C16: 0.04908897 | D16: 0.07280701 | E16: 0.14832709 | F16: 0.33095081 | G16: 0.07408897 | H16: 0.7 | I16: 25598 | J16: 45777
A17: Japanese Equity | B17: -0.0015284258 | C17: 0.027945938 | D17: 0.057420302 | E17: 0.1843258 | F17: 0.15161165 | G17: 0.052945938 | H17: 0.7 | I17: 25598 | J17: 45777
A18: Asia-Pacific Equity | B18: 0.027529177 | C18: 0.056461832 | D18: 0.085394486 | E18: 0.17102723 | F18: 0.33013357 | G18: 0.081461832 | H18: 0.7 | I18: 25626 | J18: 45777
A19: Emerging Market Equity | B19: 0.035868022 | C19: 0.075245769 | D19: 0.11462352 | E19: 0.23277046 | F19: 0.32326168 | G19: 0.10024577 | H19: 0 | I19: 32171 | J19: 45777
A20: Global REITs | B20: 0.034888826 | C20: 0.05834231 | D20: 0.081795795 | E20: 0.13562199 | F20: 0.43018326 | G20: 0.08334231 | H20: 0.7 | I20: 32720 | J20: 44925
A21: Infrastructure Equity | B21: 0.016888386 | C21: 0.04562559 | D21: 0.074362794 | E21: 0.14058985 | F21: 0.32452976 | G21: 0.07062559 | H21: 0.7 | I21: 36189 | J21: 45777
A22: Hedge Funds
A23: Event Driven | B23: 0.0078845227 | C23: 0.019381268 | D23: 0.030878014 | E23: 0.061838707 | F23: 0.31341646 | G23: 0.044381268 | H23: 1 | I23: 34365 | J23: 45777
A24: Equity Long/Short | B24: 0.0043523801 | C24: 0.020773446 | D24: 0.037194513 | E24: 0.088325647 | F24: 0.23519155 | G24: 0.045773446 | H24: 1 | I24: 34365 | J24: 45777
A25: Tactical Trading | B25: 0.0106929 | C25: 0.027968658 | D25: 0.045244417 | E25: 0.073138511 | F25: 0.38240673 | G25: 0.052968658 | H25: 1 | I25: 38383 | J25: 45777
A26: Private Equity
A27: Buyout | B27: 0.045939112 | C27: 0.075334468 | D27: 0.10472982 | E27: 0.17157286 | F27: 0.43908149 | G27: 0.10033447 | H27: 0 | I27: 25598 | J27: 45777
A28: Growth | B28: 0.044179951 | C28: 0.0774169 | D28: 0.11065385 | E28: 0.19399522 | F28: 0.39906602 | G28: 0.1024169 | H28: 0 | I28: 28886 | J28: 45777
A29: Venture | B29: 0.036776323 | C29: 0.07192664 | D29: 0.10707696 | E29: 0.20516304 | F29: 0.35058284 | G29: 0.09692664 | H29: 0 | I29: 30680 | J29: 44925
A30: Other Private Assets
A31: Private Credit | B31: 0.039932018 | C31: 0.059395007 | D31: 0.078857996 | E31: 0.11360029 | F31: 0.52284206 | G31: 0.084395007 | H31: 0 | I31: 30589 | J31: 45777
A32: Core Real Estate | B32: 0.053793531 | C32: 0.078592058 | D32: 0.10339058 | E32: 0.14474239 | F32: 0.54297884 | G32: 0.10359206 | H32: 0 | I32: 32720 | J32: 44925
A33: Infrastructure | B33: 0.03788722 | C33: 0.064566235 | D33: 0.09124525 | E33: 0.15571831 | F33: 0.41463484 | G33: 0.089566235 | H33: 0 | I33: 36189 | J33: 45777

Sheet ws_Reference
B1: nominal | C1: nominal | D1: nominal | E1: nominal | F1: real | G1: real | H1: real | I1: real | J1: net_flows | K1: net_flows | L1: net_flows | M1: net_flows | N1: real_net_flows | O1: real_net_flows | P1: real_net_flows | Q1: real_net_flows
B2: 1st %ile | C2: 10th %ile | D2: 50th %ile | E2: 90th %ile | F2: 1st %ile | G2: 10th %ile | H2: 50th %ile | I2: 90th %ile | J2: 1st %ile | K2: 10th %ile | L2: 50th %ile | M2: 90th %ile | N2: 1st %ile | O2: 10th %ile | P2: 50th %ile | Q2: 90th %ile
A3: 0 | B3: 100 | C3: 100 | D3: 100 | E3: 100 | F3: 100 | G3: 100 | H3: 100 | I3: 100 | J3: 0 | K3: 0 | L3: 0 | M3: 0 | N3: 0 | O3: 0 | P3: 0 | Q3: 0
A4: 1 | B4: 88.217405 | C4: 96.64323 | D4: 107.29642 | E4: 116.68188 | F4: 85.297094 | G4: 94.267874 | H4: 104.92998 | I4: 114.36868 | J4: 0 | K4: 0 | L4: 0 | M4: 0 | N4: 0 | O4: 0 | P4: 0 | Q4: 0
A5: 2 | B5: 89.118238 | C5: 99.042741 | D5: 113.7138 | E5: 128.29693 | F5: 84.250509 | G5: 94.173901 | H5: 108.69802 | I5: 123.00062 | J5: 0 | K5: 0 | L5: 0 | M5: 0 | N5: 0 | O5: 0 | P5: 0 | Q5: 0
A6: 3 | B6: 90.296735 | C6: 102.71006 | D6: 120.26904 | E6: 139.57687 | F6: 83.236741 | G6: 95.587953 | H6: 112.41166 | I6: 131.03864 | J6: 0 | K6: 0 | L6: 0 | M6: 0 | N6: 0 | O6: 0 | P6: 0 | Q6: 0
A7: 4 | B7: 90.454866 | C7: 106.13635 | D7: 127.9854 | E7: 152.61244 | F7: 81.988514 | G7: 96.719226 | H7: 117.14477 | I7: 140.37334 | J7: 0 | K7: 0 | L7: 0 | M7: 0 | N7: 0 | O7: 0 | P7: 0 | Q7: 0
A8: 5 | B8: 91.702934 | C8: 110.30271 | D8: 136.37634 | E8: 166.73554 | F8: 81.321928 | G8: 98.126898 | H8: 122.14269 | I8: 149.93513 | J8: 0 | K8: 0 | L8: 0 | M8: 0 | N8: 0 | O8: 0 | P8: 0 | Q8: 0
A9: 6 | B9: 92.840356 | C9: 114.48462 | D9: 144.99553 | E9: 180.78156 | F9: 80.824224 | G9: 99.735599 | H9: 127.11539 | I9: 159.35968 | J9: 0 | K9: 0 | L9: 0 | M9: 0 | N9: 0 | O9: 0 | P9: 0 | Q9: 0
A10: 7 | B10: 92.500511 | C10: 117.9424 | D10: 153.97466 | E10: 195.94827 | F10: 79.19473 | G10: 100.65287 | H10: 132.23901 | I10: 169.10811 | J10: 0 | K10: 0 | L10: 0 | M10: 0 | N10: 0 | O10: 0 | P10: 0 | Q10: 0
A11: 8 | B11: 92.948268 | C11: 121.28624 | D11: 162.42977 | E11: 211.86324 | F11: 78.714077 | G11: 101.52531 | H11: 136.85735 | I11: 179.20168 | J11: 0 | K11: 0 | L11: 0 | M11: 0 | N11: 0 | O11: 0 | P11: 0 | Q11: 0
A12: 9 | B12: 93.386123 | C12: 124.67026 | D12: 171.63207 | E12: 227.52903 | F12: 77.493828 | G12: 102.43175 | H12: 141.70121 | I12: 189.29525 | J12: 0 | K12: 0 | L12: 0 | M12: 0 | N12: 0 | O12: 0 | P12: 0 | Q12: 0
A13: 10 | B13: 94.07415 | C13: 128.42916 | D13: 180.52228 | E13: 245.41105 | F13: 76.723238 | G13: 103.41849 | H13: 146.24302 | I13: 199.41629 | J13: 0 | K13: 0 | L13: 0 | M13: 0 | N13: 0 | O13: 0 | P13: 0 | Q13: 0
A14: 11 | B14: 95.6017 | C14: 132.21919 | D14: 190.33769 | E14: 264.2301 | F14: 75.881143 | G14: 104.31491 | H14: 150.82934 | I14: 211.17047 | J14: 0 | K14: 0 | L14: 0 | M14: 0 | N14: 0 | O14: 0 | P14: 0 | Q14: 0
... A23: 20 | B23: 111.54017 | C23: 176.31985 | D23: 298.96127 | E23: 495.60218 | F23: 75.070759 | G23: 116.75994 | H23: 198.72846 | I23: 328.36231 | J23: 0 | K23: 0 | L23: 0 | M23: 0 | N23: 0 | O23: 0 | P23: 0 | Q23: 0

Sheet ws_Strategic_Asset_Allocation
B1: nominal | C1: nominal | D1: nominal | E1: nominal | G1: real | H1: real | I1: real | J1: real | K1: net_flows | L1: net_flows | M1: net_flows | N1: net_flows | O1: real_net_flows | P1: real_net_flows | Q1: real_net_flows | R1: real_net_flows
B2: 1st %ile | C2: 10th %ile | D2: 50th %ile | E2: 90th %ile | G2: 1st %ile | H2: 10th %ile | I2: 50th %ile | J2: 90th %ile | K2: 1st %ile | L2: 10th %ile | M2: 50th %ile | N2: 90th %ile | O2: 1st %ile | P2: 10th %ile | Q2: 50th %ile | R2: 90th %ile
A3: 0 | B3: 100 | C3: 100 | D3: 100 | E3: 100 | F3: 100 | G3: 100 | H3: 100 | I3: 100 | J3: 100 | K3: 0 | L3: 0 | M3: 0 | N3: 0 | O3: 0 | P3: 0 | Q3: 0 | R3: 0
A4: 1 | B4: 89.113576 | C4: 98.377107 | D4: 108.59586 | E4: 118.33502 | F4: =ws_Reference!D4 -> 107.29642 | G4: 86.199928 | H4: 96.025109 | I4: 106.03467 | J4: 116.05243 | K4: 0 | L4: 0 | M4: 0 | N4: 0 | O4: 0 | P4: 0 | Q4: 0 | R4: 0
A5: 2 | B5: 91.60163 | C5: 101.86074 | D5: 117.14981 | E5: 131.07534 | F5: =ws_Reference!D5 -> 113.7138 | G5: 86.206802 | H5: 96.769271 | I5: 111.98883 | J5: 125.81676 | K5: 0 | L5: 0 | M5: 0 | N5: 0 | O5: 0 | P5: 0 | Q5: 0 | R5: 0
A6: 3 | B6: 93.815829 | C6: 107.48327 | D6: 125.3658 | E6: 144.25405 | F6: =ws_Reference!D6 -> 120.26904 | G6: 86.446521 | H6: 99.843708 | I6: 117.23586 | J6: 135.55642 | K6: 0 | L6: 0 | M6: 0 | N6: 0 | O6: 0 | P6: 0 | Q6: 0 | R6: 0
A7: 4 | B7: 94.793557 | C7: 112.26309 | D7: 134.9112 | E7: 159.54074 | F7: =ws_Reference!D7 -> 127.9854 | G7: 85.736941 | H7: 101.9398 | I7: 123.43957 | J7: 146.90808 | K7: 0 | L7: 0 | M7: 0 | N7: 0 | O7: 0 | P7: 0 | Q7: 0 | R7: 0
A8: 5 | B8: 96.78694 | C8: 117.86434 | D8: 145.536 | E8: 176.23558 | F8: =ws_Reference!D8 -> 136.37634 | G8: 86.41932 | H8: 104.62421 | I8: 130.36687 | J8: 158.75116 | K8: 0 | L8: 0 | M8: 0 | N8: 0 | O8: 0 | P8: 0 | Q8: 0 | R8: 0
A9: 6 | B9: 99.596967 | C9: 124.17992 | D9: 156.44002 | E9: 193.44167 | F9: =ws_Reference!D9 -> 144.99553 | G9: 86.838053 | H9: 107.90169 | I9: 137.19373 | J9: 170.94379 | K9: 0 | L9: 0 | M9: 0 | N9: 0 | O9: 0 | P9: 0 | Q9: 0 | R9: 0
A10: 7 | B10: 100.39224 | C10: 128.62878 | D10: 167.66149 | E10: 212.10825 | F10: =ws_Reference!D10 -> 153.97466 | G10: 85.804362 | H10: 109.84332 | I10: 144.10517 | J10: 183.59257 | K10: 0 | L10: 0 | M10: 0 | N10: 0 | O10: 0 | P10: 0 | Q10: 0 | R10: 0
A11: 8 | B11: 102.04703 | C11: 134.10051 | D11: 179.25308 | E11: 232.20703 | F11: =ws_Reference!D11 -> 162.42977 | G11: 85.264629 | H11: 112.0173 | I11: 150.85036 | J11: 196.92951 | K11: 0 | L11: 0 | M11: 0 | N11: 0 | O11: 0 | P11: 0 | Q11: 0 | R11: 0
A12: 9 | B12: 102.1159 | C12: 138.9214 | D12: 190.96097 | E12: 253.28246 | F12: =ws_Reference!D12 -> 171.63207 | G12: 84.896639 | H12: 113.56676 | I12: 157.55937 | J12: 210.94027 | K12: 0 | L12: 0 | M12: 0 | N12: 0 | O12: 0 | P12: 0 | Q12: 0 | R12: 0
A13: 10 | B13: 104.08396 | C13: 144.71403 | D13: 203.34764 | E13: 276.25314 | F13: =ws_Reference!D13 -> 180.52228 | G13: 84.707749 | H13: 116.55528 | I13: 164.14349 | J13: 225.55396 | K13: 0 | L13: 0 | M13: 0 | N13: 0 | O13: 0 | P13: 0 | Q13: 0 | R13: 0
A14: 11 | B14: 107.00444 | C14: 150.14127 | D14: 216.01597 | E14: 299.92737 | F14: =ws_Reference!D14 -> 190.33769 | G14: 84.935365 | H14: 118.4914 | I14: 170.83428 | J14: 239.89454 | K14: 0 | L14: 0 | M14: 0 | N14: 0 | O14: 0 | P14: 0 | Q14: 0 | R14: 0
A15: 12 | B15: 108.81317 | C15: 156.35042 | D15: 229.36663 | E15: 326.72795 | F15: =ws_Reference!D15 -> 200.03642 | G15: 84.618985 | H15: 120.8821 | I15: 178.00568 | J15: 255.99569 | K15: 0 | L15: 0 | M15: 0 | N15: 0 | O15: 0 | P15: 0 | Q15: 0 | R15: 0
... A23: 20 | B23: 138.38755 | C23: 219.44409 | D23: 373.17104 | E23: 615.12421 | F23: =ws_Reference!D23 -> 298.96127 | G23: 91.979398 | H23: 145.27533 | I23: 248.64155 | J23: 408.39102 | K23: 0 | L23: 0 | M23: 0 | N23: 0 | O23: 0 | P23: 0 | Q23: 0 | R23: 0

Sheet Sheet1
A1: quintile | B1: I | C1: V
A2: 0 | B2: 0.014330327 | C2: 0.11077358
A3: 1 | B3: 0.019304864 | C3: 0.11018226
A4: 2 | B4: 0.022797452 | C4: 0.092534244
A5: 3 | B5: 0.026134515 | C5: 0.077144924
A6: 4 | B6: 0.032554216 | C6: 0.026929648

Sheet Sheet2
B1: 0.01 | C1: =B1+0.5% -> 0.015 | D1: =C1+0.5% -> 0.02 | E1: =D1+0.5% -> 0.025 | F1: =E1+0.5% -> 0.03 | G1: =F1+0.5% -> 0.035 | H1: =G1+0.5% -> 0.04 | I1: =H1+0.5% -> 0.045 | J1: =I1+0.5% -> 0.05 | ... L1: =K1+0.5% -> 0.06
B2: SAA_1.0% | C2: SAA_1.5% | D2: SAA_1.9999999999999998% | E2: SAA_2.5% | F2: SAA_3.0% | G2: SAA_3.4999999999999996% | H2: SAA_3.9999999999999996% | I2: SAA_4.5% | J2: SAA_5.0% | K2: SAA_5.499999999999999% | L2: SAA_6.0%
A3: 0 | B3: 1 | C3: 1 | D3: 1 | E3: 1 | F3: 1 | G3: 1 | H3: 1 | I3: 1 | J3: 1 | K3: 1 | L3: 1
A4: 1 | B4: 0.7338 | C4: 0.71775 | D4: 0.69375 | E4: 0.67395 | F4: 0.6617 | G4: 0.6406 | H4: 0.61555 | I4: 0.6 | J4: 0.57395 | K4: 0.5488 | L4: 0.51765
A5: 2 | B5: 0.79205 | C5: 0.76585 | D5: 0.73955 | E5: 0.71505 | F5: 0.6898 | G5: 0.65825 | H5: 0.62665 | I5: 0.5926 | J5: 0.5607 | K5: 0.5285 | L5: 0.4969
A6: 3 | B6: 0.84905 | C6: 0.82 | D6: 0.79065 | E6: 0.75815 | F6: 0.7184 | G6: 0.67675 | H6: 0.6409 | I6: 0.59755 | J6: 0.55265 | K6: 0.509 | L6: 0.46315
A7: 4 | B7: 0.87555 | C7: 0.84815 | D7: 0.8175 | E7: 0.7833 | F7: 0.74345 | G7: 0.7018 | H7: 0.6571 | I7: 0.60675 | J7: 0.556 | K7: 0.50235 | L7: 0.45315
A8: 5 | B8: 0.89715 | C8: 0.8712 | D8: 0.84065 | E8: 0.80395 | F8: 0.7633 | G8: 0.72005 | H8: 0.6729 | I8: 0.61815 | J8: 0.56085 | K8: 0.50545 | L8: 0.4451
A9: 6 | B9: 0.91385 | C9: 0.88895 | D9: 0.8587 | E9: 0.82135 | F9: 0.7801 | G9: 0.732 | H9: 0.68145 | I9: 0.62425 | J9: 0.5625 | K9: 0.50225 | L9: 0.437
A10: 7 | B10: 0.91715 | C10: 0.8953 | D10: 0.8639 | E10: 0.82835 | F10: 0.78565 | G10: 0.7362 | H10: 0.68075 | I10: 0.62435 | J10: 0.55765 | K10: 0.4953 | L10: 0.42995
A11: 8 | B11: 0.9229 | C11: 0.8988 | D11: 0.8684 | E11: 0.83245 | F11: 0.78645 | G11: 0.7361 | H11: 0.67965 | I11: 0.6198 | J11: 0.55265 | K11: 0.4823 | L11: 0.4136
A12: 9 | B12: 0.92555 | C12: 0.9 | D12: 0.8694 | E12: 0.83365 | F12: 0.7891 | G12: 0.73645 | H12: 0.67625 | I12: 0.61115 | J12: 0.5438 | K12: 0.4709 | L12: 0.39555
A13: 10 | B13: 0.93115 | C13: 0.9069 | D13: 0.8731 | E13: 0.8338 | F13: 0.78665 | G13: 0.734 | H13: 0.67225 | I13: 0.60235 | J13: 0.53005 | K13: 0.45765 | L13: 0.38115
A14: 11 | B14: 0.934 | C14: 0.9089 | D14: 0.8745 | E14: 0.83285 | F14: 0.7856 | G14: 0.7307 | H14: 0.6677 | I14: 0.59755 | J14: 0.51885 | K14: 0.4405 | L14: 0.3677
... A23: 20 | B23: 0.95695 | C23: 0.9317 | D23: 0.8995 | E23: 0.854 | F23: 0.79775 | G23: 0.7253 | H23: 0.6448 | I23: 0.557 | J23: 0.46465 | K23: 0.373 | L23: 0.2882
B24: =B48 -> 0 | C24: =C48 -> 0 | D24: =D48 -> 0 | E24: =E48 -> 0 | F24: =F48 -> 5e-05 | G24: =G48 -> 0.0001 | H24: =H48 -> 0.00095 | I24: =I48 -> 0.00495 | ... L24: =L48 -> 0.0748
B27: SAA_1.0% | C27: SAA_1.5% | D27: SAA_1.9999999999999998% | E27: SAA_2.5% | F27: SAA_3.0% | G27: SAA_3.4999999999999996% | H27: SAA_3.9999999999999996% | I27: SAA_4.5% | J27: SAA_5.0% | K27: SAA_5.499999999999999% | L27: SAA_6.0%
A28: 0 | B28: 0 | C28: 0 | D28: 0 | E28: 0 | F28: 0 | G28: 0 | H28: 0 | I28: 0 | J28: 0 | K28: 0 | L28: 0
A29: 1 | B29: 0 | C29: 0 | D29: 0 | E29: 0 | F29: 0 | G29: 0 | H29: 0 | I29: 0 | J29: 0 | K29: 0 | L29: 0
A30: 2 | B30: 0 | C30: 0 | D30: 0 | E30: 0 | F30: 0 | G30: 0 | H30: 0 | I30: 0 | J30: 0 | K30: 0 | L30: 0
A31: 3 | B31: 0 | C31: 0 | D31: 0 | E31: 0 | F31: 0 | G31: 0 | H31: 0 | I31: 0 | J31: 0 | K31: 0 | L31: 0
A32: 4 | B32: 0 | C32: 0 | D32: 0 | E32: 0 | F32: 0 | G32: 0 | H32: 0 | I32: 0 | J32: 0 | K32: 0 | L32: 0
A33: 5 | B33: 0 | C33: 0 | D33: 0 | E33: 0 | F33: 0 | G33: 0 | H33: 0 | I33: 0 | J33: 0 | K33: 0 | L33: 0
A34: 6 | B34: 0 | C34: 0 | D34: 0 | E34: 0 | F34: 0 | G34: 0 | H34: 0 | I34: 0 | J34: 0 | K34: 0 | L34: 0
A35: 7 | B35: 0 | C35: 0 | D35: 0 | E35: 0 | F35: 0 | G35: 0 | H35: 0 | I35: 0 | J35: 0 | K35: 0 | L35: 0
A36: 8 | B36: 0 | C36: 0 | D36: 0 | E36: 0 | F36: 0 | G36: 0 | H36: 0 | I36: 0 | J36: 0 | K36: 0 | L36: 0
A37: 9 | B37: 0 | C37: 0 | D37: 0 | E37: 0 | F37: 0 | G37: 0 | H37: 0 | I37: 0 | J37: 0 | K37: 0 | L37: 0
A38: 10 | B38: 0 | C38: 0 | D38: 0 | E38: 0 | F38: 0 | G38: 0 | H38: 0 | I38: 0 | J38: 0 | K38: 0 | L38: 0
A39: 11 | B39: 0 | C39: 0 | D39: 0 | E39: 0 | F39: 0 | G39: 0 | H39: 0 | I39: 0 | J39: 0 | K39: 0 | L39: 0
... A48: 20 | B48: 0 | C48: 0 | D48: 0 | E48: 0 | F48: 5e-05 | G48: 0.0001 | H48: 0.00095 | I48: 0.00495 | J48: 0.01495 | K48: 0.03545 | L48: 0.0748
