Workbook

Sheet Portfolios
B1: Low Volatility | C1: Conservative | D1: Moderate | E1: Aggressive
A2: Investment Grade Fixed Income | B2: 0.745 | C2: 58.8%% | D2: 0.36 | E2: 0.15
A3: US Dollar Debt | B3: 24.5 | C3: 58.5 | D3: 36 | E3: 15
A4: US Dollar Short Duration Fixed Income | B4: 50 | C4: - | D4: - | E4: -
A5: Other Fixed Income | B5: 0.02 | C5: 0.03 | D5: 0.045 | E5: 0.055
A6: US High Yield Bonds | B6: 2 | C6: 3 | D6: 4.5 | E6: 5.5
A7: Public Equity | B7: 0.14 | C7: 0.225 | D7: 0.355 | E7: 0.505
A8: US Large Cap Growth Equity | B8: 3.9 | C8: 6.3 | D8: 10 | E8: 14.2
A9: US Large Cap Value Equity | B9: 4.4 | C9: 7.1 | D9: 11.2 | E9: 15.9
A10: US Small Cap Equity | B10: 1.4 | C10: 2.2 | D10: 3.5 | E10: 5
A11: Europe ex-UK Equity | B11: 1.6 | C11: 2.5 | D11: 4 | E11: 5.7
A12: UK Equity | B12: 0.5 | C12: 0.8 | D12: 1.2 | E12: 1.7
A13: Japanese Equity | B13: 0.7 | C13: 1.1 | D13: 1.8 | E13: 2.6
A14: Asia-Pacific Equity | B14: 0.4 | C14: 0.6 | D14: 0.9 | E14: 1.3
A15: Emerging Market Equity | B15: 0.4 | C15: 0.6 | D15: 0.9 | E15: 1.3
A16: Global Public REITs | B16: 0.4 | C16: 0.65 | D16: 1 | E16: 1.4
... A24: Growth | B24: 1 | C24: 1.4 | D24: 2.8 | E24: 4.3
A25: Venture | B25: - | C25: - | D25: 0.8 | E25: 1.2
A26: Other Private Assets | B26: 0.04 | C26: 0.07 | D26: 0.075 | E26: 0.075
A27: Private Credit | B27: 1.3 | C27: 2.3 | D27: 3.5 | E27: 3.5
A28: Core Private Real Estate | B28: 1.35 | C28: 2.35 | D28: 2 | E28: 2
A29: Private Infrastructure | B29: 1.35 | C29: 2.35 | D29: 2 | E29: 2
A30: TOTAL | B30: 1 | C30: 1 | D30: 1 | E30: 1
A32: Estimated Mean Return (2.5% Risk Free Rate) | B32: 0.044 | C32: 0.054 | D32: 0.065 | E32: 0.076
A33: Sharpe Ratio | B33: 0.6 | C33: 0.59 | D33: 0.53 | E33: 0.49
A35: Volatility | B35: 0.031 | C35: 0.049 | D35: 0.074 | E35: 0.103
A37: Risk-Equivalent Benchmark (Bond/Equity) | B37: 80/20 | C37: 70/30 | D37: 50/50 | E37: 30/70

Sheet Sheet1
B1: Low Volatility
A2: Investment Grade Fixed Income | B2: 0.745
A3: US Dollar Debt | B3: 24.5
A4: TOTAL | B4: 1
A6: Estimated Mean Return (2.5% Risk Free Rate) | B6: 0.044
A7: Sharpe Ratio | B7: 0.6
A9: Volatility | B9: 0.031
A11: Risk-Equivalent Benchmark (Bond/Equity) | B11: 80/20

Sheet Risk-Metrics
B1: Low Volatility | D1: Conservative | F1: Moderate | H1: Aggressive
A2: Investment Grade Fixed Income | B2: 0.745 | D2: 58.8%% | F2: 0.36 | H2: 0.15
A3: Other Fixed Income | B3: 0.02 | D3: 0.03 | F3: 0.045 | H3: 0.055
A4: Public Equity | B4: 0.14 | D4: 0.225 | F4: 0.355 | H4: 0.505
A5: Hedge Funds | B5: 0.015 | D5: 0.035 | F5: 0.045 | H5: 0.03
A6: Private Equity | B6: 0.04 | D6: 0.055 | F6: 0.12 | H6: 0.185
A7: Other Private Assets | B7: 0.04 | D7: 0.07 | F7: 0.075 | H7: 0.075
A8: Estimated Mean Return (2.5% Risk Free Rate) | B8: 0.044 | D8: 0.054 | F8: 0.065 | H8: 0.076
A9: Sharpe Ratio | B9: 0.6 | D9: 0.59 | F9: 0.53 | H9: 0.49
A10: Volatility | B10: 0.031 | D10: 0.049 | F10: 0.074 | H10: 0.103
A11: Risk-Equivalent Benchmark (Bond/Equity) | B11: 80/20 | D11: 70/30 | F11: 50/50 | H11: 30/70
A12: Factor-Based Risk Analytics
A13: Predicted Performance over Stress Periods | B13: Nominal | C13: Real | D13: Nominal | E13: Real | F13: Nominal | G13: Real | H13: Nominal | I13: Real
A14: Oil Embargo (Jan 73 - Sep 74) | B14: -0.033 | C14: -0.184 | D14: -0.118 | E14: -0.256 | F14: -0.2 | G14: -0.327 | H14: -0.283 | I14: -0.395
A15: US Inflation / Iranian Revolution (Nov 78 - Mar 80) | B15: 0.07 | C15: -0.098 | D15: 0.035 | E15: -0.128 | F15: 0.056 | G15: -0.11 | H15: 0.077 | I15: -0.092
A16: US Stagflation (Nov 80 - Jul 82) | B16: 0.162 | C16: 0.02 | D16: 0.112 | E16: -0.023 | F16: 0.046 | G16: -0.082 | H16: -0.021 | I16: -0.14
A17: Black Monday (Sep 87 - Oct 87) | B17: -0.025 | C17: -0.028 | D17: -0.048 | E17: -0.05 | F17: -0.097 | G17: -0.099 | H17: -0.148 | I17: -0.15
A18: Bond Crisis (Jan 94 - Oct 94) | B18: -0.015 | C18: -0.036 | D18: -0.033 | E18: -0.053 | F18: -0.027 | G18: -0.047 | H18: -0.022 | I18: -0.042
A19: Tech Meltdown (Mar 00 - Sep 02) | B19: 0.011 | C19: -0.044 | D19: -0.049 | E19: -0.1 | F19: -0.167 | G19: -0.212 | H19: -0.275 | I19: -0.315
A20: Financial Crisis (Oct 07 - Feb 09) | B20: -0.088 | C20: -0.103 | D20: -0.159 | E20: -0.173 | F20: -0.283 | G20: -0.295 | H20: -0.393 | I20: -0.403
A21: Covid-19 (Jan 20 - Mar 20) | B21: -0.03 | C21: -0.028 | D21: -0.053 | E21: -0.051 | F21: -0.098 | G21: -0.097 | H21: -0.145 | I21: -0.143
A22: Value at Risk with 99% Confidence
A23: Over 1 Month | B23: 0.022 | D23: 0.038 | F23: 0.063 | H23: 0.089
A24: Over 1 Year | B24: 0.035 | D24: 0.082 | F24: 0.162 | H24: 0.243
A25: Over 3 Years | B25: 0 | D25: 0.044 | F25: 0.149 | H25: 0.253
A26: Probability of Loss
A27: Over 1 Month | B27: 0.238 | D27: 0.279 | F27: 0.314 | H27: 0.337
A28: Over 1 Year | B28: 0.04 | D28: 0.084 | F28: 0.143 | H28: 0.187
A29: Over 3 Years | B29: 0.008 | D29: 0.026 | F29: 0.07 | H29: 0.108
A30: Portfolio Risk Premia

Sheet Factor Charts
B1: R | C1: G | D1: B
A2: Equity | G2: 0.025
A3: Term | G3: 0.005 | I3: 0.025
A4: Funding | G4: 0.006 | I4: 0.005
A5: Liquidity | G5: 0.0025 | I5: 0.006
A6: Carry | G6: 0.0035 | I6: 0.0025
A7: Emerging Market | G7: 0.004 | I7: 0.0035
I8: 0.004

Sheet Assumptions
B1: Long-Term Estimates
B2: Risk Premium with Estimated Range | G2: Volatility | H2: Sharpe Ratio | I2: Estimated Mean Return (2.5% Risk Free Rate) | J2: Hedging Ratio
A3: Investment Grade Fixed Income
A4: US Dollar Debt | B4: 0.006 | C4: ◄ | D4: 0.011 | E4: ► | F4: 1.7%% | G4: 0.033 | H4: 0.35 | I4: =D4+2.5% -> 0.036 | J4: 0
A5: US Dollar Short Duration Fixed Income | B5: 0.001 | C5: ◄ | D5: 0.004 | E5: ► | F5: 0.7%% | G5: 0.016 | H5: 0.25 | I5: =D5+2.5% -> 0.029 | J5: 0
A6: Other Fixed Income
A7: US High Yiled Bonds | B7: 0.016 | C7: ◄ | D7: 0.035 | E7: ► | F7: 5.4%% | G7: 0.117 | H7: 0.3 | I7: =D7+2.5% -> 0.06 | J7: 0
A8: Public Equity
A9: US Large Cap Growth Equity | B9: 0.027 | C9: ◄ | D9: 0.054 | E9: ► | F9: 8.1%% | G9: 0.168 | H9: 0.32 | I9: =D9+2.5% -> 0.079 | J9: 0
A10: US Large Cap Value Equity | B10: 0.037 | C10: ◄ | D10: 0.06 | E10: ► | F10: 8.4%% | G10: 0.145 | H10: 0.41 | I10: =D10+2.5% -> 0.085 | J10: 0
A11: US Small Cap Equity | B11: 0.032 | C11: ◄ | D11: 0.063 | E11: ► | F11: 9.4%% | G11: 0.191 | H11: 0.33 | I11: =D11+2.5% -> 0.088 | J11: 0
A12: Europe ex-UK Equity | B12: 0.021 | C12: ◄ | D12: 0.048 | E12: ► | F12: 7.4%% | G12: 0.164 | H12: 0.29 | I12: =D12+2.5% -> 0.073 | J12: 0.7
A13: UK Equity | B13: 0.026 | C13: ◄ | D13: 0.051 | E13: ► | F13: 7.5%% | G13: 0.151 | H13: 0.34 | I13: =D13+2.5% -> 0.076 | J13: 0.7
A14: Japanese Equity | B14: -0.006 | C14: ◄ | D14: 0.026 | E14: ► | F14: 5.7%% | G14: 0.164 | H14: 0.16 | I14: =D14+2.5% -> 0.051 | J14: 0.7
A15: Asia-Pacific Equity | B15: 0.04 | C15: ◄ | D15: 0.069 | E15: ► | F15: 9.9%% | G15: 0.181 | H15: 0.38 | I15: =D15+2.5% -> 0.094 | J15: 0.7
A16: Emerging Market Equity | B16: 0.02 | C16: ◄ | D16: 0.086 | E16: ► | F16: 15.1%% | G16: 0.22 | H16: 0.39 | I16: =D16+2.5% -> 0.111 | J16: 0
A17: Global Public REITs | B17: 0.03 | C17: ◄ | D17: 0.061 | E17: ► | F17: 9.2%% | G17: 0.162 | H17: 0.38 | I17: =D17+2.5% -> 0.086 | J17: 0.7
A18: Global Infrastructure Equity | B18: 0.019 | C18: ◄ | D18: 0.048 | E18: ► | F18: 7.7%% | G18: 0.14 | H18: 0.34 | I18: =D18+2.5% -> 0.073 | J18: 0.7
A19: Hedge Funds
A20: Event Driven | B20: -0.006 | C20: ◄ | D20: 0.019 | E20: ► | F20: 4.3%% | G20: 0.064 | H20: 0.29 | I20: =D20+2.5% -> 0.044 | J20: 1
A21: Equity Long/Short | B21: -0.006 | C21: ◄ | D21: 0.027 | E21: ► | F21: 6.1%% | G21: 0.088 | H21: 0.31 | I21: =D21+2.5% -> 0.052 | J21: 1
A22: Tactical Trading | B22: -0.002 | C22: ◄ | D22: 0.029 | E22: ► | F22: 5.9%% | G22: 0.081 | H22: 0.35 | I22: =D22+2.5% -> 0.054 | J22: 1
A23: Private Equity
A24: Buyout | B24: 0.048 | C24: ◄ | D24: 0.08 | E24: ► | F24: 0.113 | G24: 0.162 | H24: 0.51 | I24: =D24+2.5% -> 0.105 | J24: 0
A25: Growth | B25: 0.049 | C25: ◄ | D25: 0.082 | E25: ► | F25: 0.115 | G25: 0.228 | H25: 0.51 | I25: =D25+2.5% -> 0.107 | J25: 0
A26: Venture | B26: 0.026 | C26: ◄ | D26: 0.073 | E26: ► | F26: 12.0%% | G26: 0.228 | H26: 0.32 | I26: =D26+2.5% -> 0.098 | J26: 0
A27: Other Private Assets
A28: Private Credit | B28: 0.022 | C28: ◄ | D28: 0.044 | E28: ► | F28: 6.7%% | G28: 0.11 | H28: 0.4 | I28: =D28+2.5% -> 0.069 | J28: 0
A29: Core Private Real Estate | B29: 0.023 | C29: ◄ | D29: 0.038 | E29: ► | F29: 5.3%% | G29: 0.072 | H29: 0.53 | I29: =D29+2.5% -> 0.063 | J29: 0
A30: Private Infrastructure | B30: 0.026 | C30: ◄ | D30: 0.043 | E30: ► | F30: 6.0%% | G30: 0.084 | H30: 0.51 | I30: =D30+2.5% -> 0.068 | J30: 0

Sheet Sheet4
B1: Long-Term Estimates | I1: Modelling Dates
B2: Risk Premia with Estimated Range | E2: Volatility | F2: Sharpe Ratio | G2: Estimated Mean Return (2.5% Risk Free Rate) | H2: Hedging Ratio | I2: From | J2: To
A3: Investment Grade Fixed Income
A4: US Dollar Debt | B4: 0.0057241237 | C4: 0.010852468 | D4: 0.015980812 | E4: 0.032071469 | F4: 0.33838387 | G4: 0.035852468 | H4: 0 | I4: 26723 | J4: 45777
A5: US Dollar Short Duration Debt | B5: 0.00043297126 | C5: 0.0030821904 | D5: 0.0057314095 | E5: 0.014716287 | F5: 0.20944076 | G5: 0.02808219 | H5: 0 | I5: 33662 | J5: 45777
A6: Other Fixed Income
A7: US High Yield Bonds | B7: 0.026403977 | C7: 0.043364015 | D7: 0.060324053 | E7: 0.10606412 | F7: 0.40884716 | G7: 0.068364015 | H7: 0 | I7: 30589 | J7: 45777
A8: Public Equity
A9: US Large Cap Growth Equity | B9: 0.017523011 | C9: 0.044567317 | D9: 0.071611624 | E9: 0.16912879 | F9: 0.26351112 | G9: 0.069567317 | H9: 0 | I9: 28886 | J9: 45777
A10: US Large Cap Value Equity | B10: 0.037739775 | C10: 0.060989627 | D10: 0.08423948 | E10: 0.14539916 | F10: 0.41946341 | G10: 0.085989627 | H10: 0 | I10: 28886 | J10: 45777
A11: US Small Cap Equity | B11: 0.039116118 | C11: 0.069881104 | D11: 0.10064609 | E11: 0.19239704 | F11: 0.36321298 | G11: 0.094881104 | H11: 0 | I11: 28886 | J11: 45777
A12: Europe ex-UK Equity | B12: 0.020982633 | C12: 0.047043209 | D12: 0.073103784 | E12: 0.16297676 | F12: 0.28864979 | G12: 0.072043209 | H12: 0.7 | I12: 25626 | J12: 45777
A13: UK Equity | B13: 0.02523743 | C13: 0.048975927 | D13: 0.072714423 | E13: 0.14845502 | F13: 0.32990414 | G13: 0.073975927 | H13: 0.7 | I13: 25598 | J13: 45777
A14: Japanese Equity | B14: -0.0011545953 | C14: 0.028252356 | D14: 0.057659307 | E14: 0.18390422 | F14: 0.15362538 | G14: 0.053252356 | H14: 0.7 | I14: 25598 | J14: 45777
A15: Asia-Pacific Equity | B15: 0.027437055 | C15: 0.056359981 | D15: 0.085282906 | E15: 0.17096972 | F15: 0.3296489 | G15: 0.081359981 | H15: 0.7 | I15: 25626 | J15: 45777
A16: Emerging Market Equity | B16: 0.035865029 | C16: 0.075241693 | D16: 0.11461836 | E16: 0.23276405 | F16: 0.32325306 | G16: 0.10024169 | H16: 0 | I16: 32171 | J16: 45777
A17: Global REITs | B17: 0.039211524 | C17: 0.064800724 | D17: 0.090389925 | E17: 0.14797197 | F17: 0.43792566 | G17: 0.089800724 | H17: 0.7 | I17: 32720 | J17: 45777
A18: Infrastructure Equity | B18: 0.016403181 | C18: 0.044976837 | D18: 0.073550492 | E18: 0.13978973 | F18: 0.32174636 | G18: 0.069976837 | H18: 0.7 | I18: 36189 | J18: 45777
A19: Hedge Funds
A20: Event Driven | B20: 0.0076750631 | C20: 0.019169505 | D20: 0.030663948 | E20: 0.061826318 | F20: 0.31005413 | G20: 0.044169505 | H20: 1 | I20: 34365 | J20: 45777
A21: Equity Long/Short | B21: 0.0043657889 | C21: 0.020771382 | D21: 0.037176976 | E21: 0.088242422 | F21: 0.23538998 | G21: 0.045771382 | H21: 1 | I21: 34365 | J21: 45777
A22: Tactical Trading | B22: 0.0034812134 | C22: 0.018658048 | D22: 0.033834883 | E22: 0.081633173 | F22: 0.22855963 | G22: 0.043658048 | H22: 1 | I22: 34365 | J22: 45777
A23: Private Equity
A24: Buyout | B24: 0.026608812 | C24: 0.050216749 | D24: 0.073824687 | E24: 0.14763854 | F24: 0.34013307 | G24: 0.075216749 | H24: 0 | I24: 25598 | J24: 45777
A25: Growth | B25: 0.017870761 | C25: 0.035944264 | D25: 0.054017768 | E25: 0.097213778 | F25: 0.36974455 | G25: 0.060944264 | H25: 0 | I25: 34365 | J25: 45777
A26: Venture | B26: 0.013852678 | C26: 0.047598983 | D26: 0.081345289 | E26: 0.21081963 | F26: 0.22578061 | G26: 0.072598983 | H26: 0 | I26: 30680 | J26: 44925
A27: Other Private Assets
A28: Private Credit | B28: 0.026403977 | C28: 0.043364015 | D28: 0.060324053 | E28: 0.10606412 | F28: 0.40884716 | G28: 0.068364015 | H28: 0 | I28: 30589 | J28: 45777
A29: Core Real Estate | B29: 0.039132178 | C29: 0.062011236 | D29: 0.084890293 | E29: 0.14308029 | F29: 0.43340166 | G29: 0.087011236 | H29: 0 | I29: 30650 | J29: 44925
A30: Infrastructure | B30: 0.013852678 | C30: 0.047598983 | D30: 0.081345289 | E30: 0.21081963 | F30: 0.22578061 | G30: 0.072598983 | H30: 0 | I30: 30680 | J30: 44925

Sheet RAW WEIGHTS
A1: Codes | B1: Reporting Name | C1: Category | D1: Low Volatility | E1: Conservative | F1: Moderate | G1: Aggressive | H1: Hedge Ratios
A2: LHTRYIN | B2: US Dollar Debt | C2: Investment Grade Fixed Income | D2: 0.245 | E2: 0.585 | F2: 0.36 | G2: 0.15 | H2: 0
A3: LHUT1T3 | B3: US Dollar Short Duration Debt | C3: Investment Grade Fixed Income | D3: 0.5 | E3: - | F3: - | G3: - | H3: 0
A4: LHYIELD_GE20 | B4: US High Yield Bonds | C4: Other Fixed Income | D4: 0.02 | E4: 0.03 | F4: 0.045 | G4: 0.055 | H4: 0
A5: FRUS1GR | B5: US Large Cap Growth Equity | C5: Public Equity | D5: 0.039 | E5: 0.063 | F5: 0.1 | G5: 0.142 | H5: 0
A6: FRUS1VA | B6: US Large Cap Value Equity | C6: Public Equity | D6: 0.044 | E6: 0.071 | F6: 0.112 | G6: 0.159 | H6: 0
A7: FRUSS2L | B7: US Small Cap Equity | C7: Public Equity | D7: 0.014 | E7: 0.022 | F7: 0.035 | G7: 0.05 | H7: 0
A8: MSEXUKL | B8: Europe ex-UK Equity | C8: Public Equity | D8: 0.016 | E8: 0.025 | F8: 0.04 | G8: 0.057 | H8: 0.7
A9: MSUTDKL | B9: UK Equity | C9: Public Equity | D9: 0.005 | E9: 0.008 | F9: 0.012 | G9: 0.017 | H9: 0.7
A10: MSJPANL | B10: Japanese Equity | C10: Public Equity | D10: 0.007 | E10: 0.011 | F10: 0.018 | G10: 0.026 | H10: 0.7
A11: MSPXJPL | B11: Asia-Pacific Equity | C11: Public Equity | D11: 0.004 | E11: 0.006 | F11: 0.009 | G11: 0.013 | H11: 0.7
A12: MSEMKF$ | B12: Emerging Market Equity | C12: Public Equity | D12: 0.004 | E12: 0.006 | F12: 0.009 | G12: 0.013 | H12: 0
A13: SBBRGLL | B13: Global REITs | C13: Public Equity | D13: 0.004 | E13: 0.0065 | F13: 0.01 | G13: 0.014 | H13: 0.7
A14: INFRA_EQUITY | B14: Infrastructure Equity | C14: Public Equity | D14: 0.004 | E14: 0.0065 | F14: 0.01 | G14: 0.014 | H14: 0.7
A15: CSTEVDH | B15: Event Driven | C15: Hedge Funds | D15: 0.003 | E15: 0.007 | F15: 0.009 | G15: 0.006 | H15: 1
... A23: PA_INFRA | B23: Infrastructure | C23: Other Private Assets | D23: 0.0135 | E23: 0.0235 | F23: 0.02 | G23: 0.02 | H23: 0
B24: Total | D24: =SUM(D2:D23) -> 1.001 | E24: =SUM(E2:E23) -> 1 | F24: =SUM(F2:F23) -> 1 | G24: =SUM(G2:G23) -> 1

Sheet Sheet3
B1: Long-Term Estimates | I1: Modelling Dates
B2: Lower Range | C2: Risk Premia with Estimated Range | D2: Upper Range | E2: Volatility | F2: Sharpe Ratio | G2: Estimated Mean Return (2.5% Risk Free Rate) | H2: Hedging Ratio | I2: From | J2: To | K2: ISG | L2: FB | M2: Diff
A3: Fixed Income
A4: Bloomberg U.S. Treasury: Intermediate USD | B4: 0.0057241237 | C4: 0.010852468 | D4: 0.015980812 | E4: 0.032071469 | F4: 0.33838387 | G4: 0.035852468 | H4: 0 | I4: 26723 | J4: 45777 | K4: =Assumptions!D4 -> 0.011 | L4: =C4 -> 0.010852468 | M4: =L4-K4 -> -0.00014753216
A5: Bloomberg U.S. Treasury: 1-3 Year USD | B5: 0.00043297126 | C5: 0.0030821904 | D5: 0.0057314095 | E5: 0.014716287 | F5: 0.20944076 | G5: 0.02808219 | H5: 0 | I5: 33662 | J5: 45777 | K5: =Assumptions!D5 -> 0.004 | L5: =C5 -> 0.0030821904 | M5: =L5-K5 -> -0.00091780963
A6: Other Fixed Income
A7: US High Yield | B7: 0.026403977 | C7: 0.043364015 | D7: 0.060324053 | E7: 0.10606412 | F7: 0.40884716 | G7: 0.068364015 | H7: 0 | I7: 30589 | J7: 45777 | K7: =Assumptions!D7 -> 0.035 | L7: =C7 -> 0.043364015 | M7: =L7-K7 -> 0.0083640154
A8: Public Equity
A9: Russell 1000 (EOD) Growth | B9: 0.017523011 | C9: 0.044567317 | D9: 0.071611624 | E9: 0.16912879 | F9: 0.26351112 | G9: 0.069567317 | H9: 0 | I9: 28886 | J9: 45777 | K9: =Assumptions!D9 -> 0.054 | L9: =C9 -> 0.044567317 | M9: =L9-K9 -> -0.0094326826
A10: Russell 1000 (EOD) Value | B10: 0.037739775 | C10: 0.060989627 | D10: 0.08423948 | E10: 0.14539916 | F10: 0.41946341 | G10: 0.085989627 | H10: 0 | I10: 28886 | J10: 45777 | K10: =Assumptions!D10 -> 0.06 | L10: =C10 -> 0.060989627 | M10: =L10-K10 -> 0.00098962723
A11: Russell 2000 (EOD) | B11: 0.039116118 | C11: 0.069881104 | D11: 0.10064609 | E11: 0.19239704 | F11: 0.36321298 | G11: 0.094881104 | H11: 0 | I11: 28886 | J11: 45777 | K11: =Assumptions!D11 -> 0.063 | L11: =C11 -> 0.069881104 | M11: =L11-K11 -> 0.0068811036
A12: MSCI Europe Excluding United Kingdom | B12: 0.020982633 | C12: 0.047043209 | D12: 0.073103784 | E12: 0.16297676 | F12: 0.28864979 | G12: 0.072043209 | H12: 0.7 | I12: 25626 | J12: 45777 | K12: =Assumptions!D12 -> 0.048 | L12: =C12 -> 0.047043209 | M12: =L12-K12 -> -0.00095679127
A13: MSCI United Kingdom | B13: 0.02523743 | C13: 0.048975927 | D13: 0.072714423 | E13: 0.14845502 | F13: 0.32990414 | G13: 0.073975927 | H13: 0.7 | I13: 25598 | J13: 45777 | K13: =Assumptions!D13 -> 0.051 | L13: =C13 -> 0.048975927 | M13: =L13-K13 -> -0.0020240732
A14: MSCI Japan | B14: -0.0011545953 | C14: 0.028252356 | D14: 0.057659307 | E14: 0.18390422 | F14: 0.15362538 | G14: 0.053252356 | H14: 0.7 | I14: 25598 | J14: 45777 | K14: =Assumptions!D14 -> 0.026 | L14: =C14 -> 0.028252356 | M14: =L14-K14 -> 0.0022523559
A15: MSCI Pacific Excluding Japan | B15: 0.027437055 | C15: 0.056359981 | D15: 0.085282906 | E15: 0.17096972 | F15: 0.3296489 | G15: 0.081359981 | H15: 0.7 | I15: 25626 | J15: 45777 | K15: =Assumptions!D15 -> 0.069 | L15: =C15 -> 0.056359981 | M15: =L15-K15 -> -0.012640019
A16: MSCI Emerging Markets United States Dollar | B16: 0.035865029 | C16: 0.075241693 | D16: 0.11461836 | E16: 0.23276405 | F16: 0.32325306 | G16: 0.10024169 | H16: 0 | I16: 32171 | J16: 45777 | K16: =Assumptions!D16 -> 0.086 | L16: =C16 -> 0.075241693 | M16: =L16-K16 -> -0.010758307
A17: Standard and Poor's Global Real Estate Investment Trusts (REITS) | B17: 0.039211524 | C17: 0.064800724 | D17: 0.090389925 | E17: 0.14797197 | F17: 0.43792566 | G17: 0.089800724 | H17: 0.7 | I17: 32720 | J17: 45777 | K17: =Assumptions!D17 -> 0.061 | L17: =C17 -> 0.064800724 | M17: =L17-K17 -> 0.0038007241
A18: Infrastructure Equity | B18: 0.016403181 | C18: 0.044976837 | D18: 0.073550492 | E18: 0.13978973 | F18: 0.32174636 | G18: 0.069976837 | H18: 0.7 | I18: 36189 | J18: 45777 | K18: =Assumptions!D18 -> 0.048 | L18: =C18 -> 0.044976837 | M18: =L18-K18 -> -0.0030231633
A19: Hedge Funds
A20: CREDIT SUISSE HEDGE EVENT DRIVEN $ | B20: 0.0076750631 | C20: 0.019169505 | D20: 0.030663948 | E20: 0.061826318 | F20: 0.31005413 | G20: 0.044169505 | H20: 1 | I20: 34365 | J20: 45777 | K20: =Assumptions!D20 -> 0.019 | L20: =C20 -> 0.019169505 | M20: =L20-K20 -> 0.00016950547
A21: CREDIT SUISSE HEDGE LONG/SHORT EQTY$ | B21: 0.0043657889 | C21: 0.020771382 | D21: 0.037176976 | E21: 0.088242422 | F21: 0.23538998 | G21: 0.045771382 | H21: 1 | I21: 34365 | J21: 45777 | K21: =Assumptions!D21 -> 0.027 | L21: =C21 -> 0.020771382 | M21: =L21-K21 -> -0.0062286177
A22: Tactical Trading | B22: 0.0034812134 | C22: 0.018658048 | D22: 0.033834883 | E22: 0.081633173 | F22: 0.22855963 | G22: 0.043658048 | H22: 1 | I22: 34365 | J22: 45777 | K22: =Assumptions!D22 -> 0.029 | L22: =C22 -> 0.018658048 | M22: =L22-K22 -> -0.010341952
A23: Private Equity
A24: Buyout | B24: 0.026608812 | C24: 0.050216749 | D24: 0.073824687 | E24: 0.14763854 | F24: 0.34013307 | G24: 0.075216749 | H24: 0 | I24: 25598 | J24: 45777 | K24: =Assumptions!D24 -> 0.08 | L24: =C24 -> 0.050216749 | M24: =L24-K24 -> -0.029783251
A25: Distressed | B25: 0.017870761 | C25: 0.035944264 | D25: 0.054017768 | E25: 0.097213778 | F25: 0.36974455 | G25: 0.060944264 | H25: 0 | I25: 34365 | J25: 45777 | K25: =Assumptions!D25 -> 0.082 | L25: =C25 -> 0.035944264 | M25: =L25-K25 -> -0.046055736
A26: Venture | B26: 0.013852678 | C26: 0.047598983 | D26: 0.081345289 | E26: 0.21081963 | F26: 0.22578061 | G26: 0.072598983 | H26: 0 | I26: 30680 | J26: 44925 | K26: =Assumptions!D26 -> 0.073 | L26: =C26 -> 0.047598983 | M26: =L26-K26 -> -0.025401017
A27: Other Private Assets
A28: Private Credit | B28: 0.026403977 | C28: 0.043364015 | D28: 0.060324053 | E28: 0.10606412 | F28: 0.40884716 | G28: 0.068364015 | H28: 0 | I28: 30589 | J28: 45777 | K28: =Assumptions!D28 -> 0.044 | L28: =C28 -> 0.043364015 | M28: =L28-K28 -> -0.00063598459
A29: Private Real Estate | B29: 0.039132178 | C29: 0.062011236 | D29: 0.084890293 | E29: 0.14308029 | F29: 0.43340166 | G29: 0.087011236 | H29: 0 | I29: 30650 | J29: 44925 | K29: =Assumptions!D29 -> 0.038 | L29: =C29 -> 0.062011236 | M29: =L29-K29 -> 0.024011236
A30: Infrastructure | B30: 0.013852678 | C30: 0.047598983 | D30: 0.081345289 | E30: 0.21081963 | F30: 0.22578061 | G30: 0.072598983 | H30: 0 | I30: 30680 | J30: 44925 | K30: =Assumptions!D30 -> 0.043 | L30: =C30 -> 0.047598983 | M30: =L30-K30 -> 0.0045989834

Sheet Sheet2
A1: A1 | B1: P1
A2: AC | B2: PC
A3: AS | B3: PS
A4: AT | B4: PT
A6: O | B6: O
A7: O | B7: O
A9: O | B9: O
A11: O | B11: O

Sheet Sheet4 (2)
B1: Long-Term Estimates | I1: Modelling Dates
B2: Risk Premia with Estimated Range | E2: Volatility | F2: Sharpe Ratio | G2: Estimated Mean Return (2.5% Risk Free Rate) | H2: Hedging Ratio | I2: From | J2: To
A3: Investment Grade Fixed Income
A4: US Dollar Debt | B4: 0.0057241237 | C4: 0.010852468 | D4: 0.015980812 | E4: 0.032071469 | F4: 0.33838387 | G4: 0.035852468 | H4: 0 | I4: 26723 | J4: 45777
A5: Other Fixed Income
